selenium_tkit/__init__.py
selenium_tkit/chrome.py
selenium_tkit/custom_webdriver.py
selenium_tkit/edge.py
selenium_tkit/firefox.py
selenium_tkit-0.1.0.3.dist-info/LICENSE
selenium_tkit-0.1.0.3.dist-info/METADATA
selenium_tkit-0.1.0.3.dist-info/WHEEL
selenium_tkit-0.1.0.3.dist-info/RECORD
