Metadata-Version: 2.1
Name: selenium-tkit
Version: 0.1.0.3
Summary: Another selenium toolkit
Author: henrique lino
Author-email: henrique.lino97@gmail.com
Requires-Python: >=3.9,<4.0
Classifier: Programming Language :: Python :: 3
Classifier: Programming Language :: Python :: 3.9
Classifier: Programming Language :: Python :: 3.10
Classifier: Programming Language :: Python :: 3.11
Requires-Dist: fake-useragent (>=1.1.1,<2.0.0)
Requires-Dist: psutil (>=5.9.4,<6.0.0)
Requires-Dist: retimer (>=0.1.0.9,<0.2.0.0)
Requires-Dist: selenium (>=4.7.2,<5.0.0)
Requires-Dist: undetected-chromedriver (>=3.1.7,<4.0.0)
Requires-Dist: webdriver-manager (>=4.0.0,<5.0.0)
